blake2signer/__init__.py
blake2signer/bases.py
blake2signer/compressors.py
blake2signer/encoders.py
blake2signer/errors.py
blake2signer/hashers/__init__.py
blake2signer/hashers/blake3_package.py
blake2signer/hashers/blakehashers.py
blake2signer/interfaces.py
blake2signer/mixins.py
blake2signer/py.typed
blake2signer/serializers.py
blake2signer/signers.py
blake2signer/tests/__init__.py
blake2signer/tests/bases.py
blake2signer/tests/test_hashers.py
blake2signer/tests/test_serializersigner.py
blake2signer/tests/test_signer.py
blake2signer/tests/test_timestampsigner.py
blake2signer/tests/test_utils.py
blake2signer/utils.py
blake2signer-4.0.0.dist-info/LICENSE
blake2signer-4.0.0.dist-info/METADATA
blake2signer-4.0.0.dist-info/WHEEL
blake2signer-4.0.0.dist-info/RECORD
