Metadata-Version: 2.3
Name: blake2signer
Version: 4.0.0
Summary: A library to use BLAKE in keyed hashing mode to sign and verify signed data
License: MPL-2.0
Keywords: blake,crypto,cryptography,digest,hashing,keyed-hashing,mac,signature,signer
Author: HacKan
Author-email: hackan@gmail.com
Maintainer: Erus
Maintainer-email: erudyn@protonmail.com
Requires-Python: >=3.9
Classifier: Development Status :: 5 - Production/Stable
Classifier: Intended Audience :: Developers
Classifier: License :: OSI Approved :: Mozilla Public License 2.0 (MPL 2.0)
Classifier: Natural Language :: English
Classifier: Operating System :: POSIX :: Linux
Classifier: Programming Language :: Python :: 3 :: Only
Classifier: Programming Language :: Python :: 3.9
Classifier: Programming Language :: Python :: 3.10
Classifier: Programming Language :: Python :: 3.11
Classifier: Programming Language :: Python :: 3.12
Classifier: Programming Language :: Python :: 3.13
Classifier: Programming Language :: Python :: Implementation :: CPython
Classifier: Programming Language :: Python :: Implementation :: PyPy
Classifier: Topic :: Security :: Cryptography
Classifier: Topic :: Software Development :: Libraries :: Python Modules
Classifier: Typing :: Typed
Provides-Extra: blake3
Requires-Dist: blake3 (>1.0.0) ; extra == "blake3"
Project-URL: Changelog, https://blake2signer.hackan.net/en/latest/changelog
Project-URL: Documentation, https://blake2signer.hackan.net
Project-URL: Issues, https://gitlab.com/hackancuba/blake2signer/-/issues
Project-URL: Repository, https://gitlab.com/hackancuba/blake2signer
